primapy_hub/__init__.py
primapy_hub-0.1.0.dist-info/WHEEL
primapy_hub-0.1.0.dist-info/METADATA
primapy_hub-0.1.0.dist-info/RECORD
